
{
  "header": {
    "event": "Allocation failed - JavaScript heap out of memory",
    "trigger": "FatalError",
    "filename": "report.20220506.095616.12420.0.001.json",
    "dumpEventTime": "2022-05-06T09:56:16Z",
    "dumpEventTimeStamp": "1651805776325",
    "processId": 12420,
    "cwd": "/root/MEW/SardisChain/JchainWallet",
    "commandLine": [
      "node",
      "/root/MEW/SardisChain/JchainWallet/node_modules/.bin/vue-cli-service",
      "build"
    ],
    "nodejsVersion": "v12.2.0",
    "glibcVersionRuntime": "2.17",
    "glibcVersionCompiler": "2.17",
    "wordSize": 64,
    "arch": "x64",
    "platform": "linux",
    "componentVersions": {
      "node": "12.2.0",
      "v8": "7.4.288.21-node.17",
      "uv": "1.28.0",
      "zlib": "1.2.11",
      "brotli": "1.0.7",
      "ares": "1.15.0",
      "modules": "72",
      "nghttp2": "1.38.0",
      "napi": "4",
      "llhttp": "1.1.3",
      "http_parser": "2.8.0",
      "openssl": "1.1.1b",
      "cldr": "35.1",
      "icu": "64.2",
      "tz": "2019a",
      "unicode": "12.1"
    },
    "release": {
      "name": "node",
      "headersUrl": "https://nodejs.org/download/release/v12.2.0/node-v12.2.0-headers.tar.gz",
      "sourceUrl": "https://nodejs.org/download/release/v12.2.0/node-v12.2.0.tar.gz"
    },
    "osName": "Linux",
    "osRelease": "3.10.0-1160.24.1.el7.x86_64",
    "osVersion": "#1 SMP Thu Apr 8 19:51:47 UTC 2021",
    "osMachine": "x86_64",
    "host": "server98"
  },
  "javascriptStack": {
    "message": "No stack.",
    "stack": [
      "Unavailable."
    ]
  },
  "nativeStack": [
    {
      "pc": "0x0000000000aa94ed",
      "symbol": "report::TriggerNodeReport(v8::Isolate*, node::Environment*, char const*, char const*, std::string const&, v8::Local<v8::String>) [node]"
    },
    {
      "pc": "0x000000000098d653",
      "symbol": "node::OnFatalError(char const*, char const*) [node]"
    },
    {
      "pc": "0x0000000000b077ce",
      "symbol": "v8::Utils::ReportOOMFailure(v8::internal::Isolate*, char const*, bool) [node]"
    },
    {
      "pc": "0x0000000000b07b49",
      "symbol": "v8::internal::V8::FatalProcessOutOfMemory(v8::internal::Isolate*, char const*, bool) [node]"
    },
    {
      "pc": "0x0000000000f12c05",
      "symbol": " [node]"
    },
    {
      "pc": "0x0000000000f1d56b",
      "symbol": "v8::internal::Heap::PerformGarbageCollection(v8::internal::GarbageCollector, v8::GCCallbackFlags) [node]"
    },
    {
      "pc": "0x0000000000f1e287",
      "symbol": "v8::internal::Heap::CollectGarbage(v8::internal::AllocationSpace, v8::internal::GarbageCollectionReason, v8::GCCallbackFlags) [node]"
    },
    {
      "pc": "0x0000000000f20d25",
      "symbol": "v8::internal::Heap::AllocateRawWithRetryOrFail(int, v8::internal::AllocationType, v8::internal::AllocationAlignment) [node]"
    },
    {
      "pc": "0x0000000000eebd50",
      "symbol": "v8::internal::Factory::NewFillerObject(int, bool, v8::internal::AllocationSpace) [node]"
    },
    {
      "pc": "0x00000000011bdb5e",
      "symbol": "v8::internal::Runtime_AllocateInNewSpace(int, unsigned long*, v8::internal::Isolate*) [node]"
    },
    {
      "pc": "0x0000000001a86142",
      "symbol": " [node]"
    }
  ],
  "javascriptHeap": {
    "totalMemory": 2197032960,
    "totalCommittedMemory": 2195471056,
    "usedMemory": 2108156376,
    "availableMemory": 42664704,
    "memoryLimit": 2197815296,
    "heapSpaces": {
      "read_only_space": {
        "memorySize": 524288,
        "committedMemory": 32024,
        "capacity": 523976,
        "used": 31712,
        "available": 492264
      },
      "new_space": {
        "memorySize": 33554432,
        "committedMemory": 33552752,
        "capacity": 16767232,
        "used": 5461392,
        "available": 11305840
      },
      "old_space": {
        "memorySize": 1611259904,
        "committedMemory": 1610566712,
        "capacity": 1584995840,
        "used": 1571678808,
        "available": 13317032
      },
      "code_space": {
        "memorySize": 4358144,
        "committedMemory": 4209408,
        "capacity": 3901600,
        "used": 3901600,
        "available": 0
      },
      "map_space": {
        "memorySize": 38277120,
        "committedMemory": 38051088,
        "capacity": 18414800,
        "used": 18414800,
        "available": 0
      },
      "large_object_space": {
        "memorySize": 507854848,
        "committedMemory": 507854848,
        "capacity": 507567424,
        "used": 507567424,
        "available": 0
      },
      "code_large_object_space": {
        "memorySize": 1204224,
        "committedMemory": 1204224,
        "capacity": 1100640,
        "used": 1100640,
        "available": 0
      },
      "new_large_object_space": {
        "memorySize": 0,
        "committedMemory": 0,
        "capacity": 16767232,
        "used": 0,
        "available": 16767232
      }
    }
  },
  "resourceUsage": {
    "userCpuSeconds": 332.851,
    "kernelCpuSeconds": 15.1709,
    "cpuConsumptionPercent": 178.473,
    "maxRss": 2395906048,
    "pageFaults": {
      "IORequired": 0,
      "IONotRequired": 2627662
    },
    "fsActivity": {
      "reads": 0,
      "writes": 79816
    }
  },
  "uvthreadResourceUsage": {
    "userCpuSeconds": 174.34,
    "kernelCpuSeconds": 6.62494,
    "cpuConsumptionPercent": 92.8023,
    "fsActivity": {
      "reads": 0,
      "writes": 0
    }
  },
  "libuv": [
  ],
  "environmentVariables": {
    "npm_config_save_dev": "",
    "npm_config_legacy_bundling": "",
    "npm_config_dry_run": "",
    "npm_package_engines_npm": ">= 6.0.0",
    "SUBNETWORK": "5DAX Chain",
    "npm_config_viewer": "man",
    "npm_config_only": "",
    "npm_config_commit_hooks": "true",
    "npm_config_browser": "",
    "npm_package_gitHead": "eee45256dbd83da7ffae7a0f0144222d81894839",
    "npm_package_devDependencies_prettier": "2.6.2",
    "npm_package_devDependencies_postcss_import": "12.0.1",
    "npm_package_devDependencies_ethereumjs_util": "7.1.4",
    "npm_package_devDependencies_ethereumjs_tx": "2.1.2",
    "npm_package_devDependencies_apollo": "2.33.10",
    "npm_package_dependencies_apollo_utilities": "1.3.4",
    "npm_config_also": "",
    "npm_package_dependencies_merkletreejs": "0.2.31",
    "npm_package_scripts_lint_styles": "prettier --write 'src/**/*.{scss,css}' && stylelint 'src/**/*.{scss,css}' --fix",
    "XDG_SESSION_ID": "5772",
    "npm_config_sign_git_commit": "",
    "npm_config_rollback": "true",
    "npm_package_devDependencies_web3_utils": "1.5.0",
    "npm_package_scripts_lint_code": "vue-cli-service lint --fix",
    "HOSTNAME": "server98",
    "TERM_PROGRAM": "vscode",
    "NODE": "/root/.nvm/versions/node/v12.2.0/bin/node",
    "npm_config_usage": "",
    "npm_config_audit": "true",
    "npm_package_resolutions_follow_redirects": "1.14.9",
    "npm_package_devDependencies_web3_core_requestmanager": "1.5.0",
    "npm_package_dependencies_subscriptions_transport_ws": "0.11.0",
    "npm_package_dependencies__shapeshiftoss_hdwallet_core": "1.21.1",
    "INIT_CWD": "/root/MEW/SardisChain/JchainWallet",
    "npm_package_homepage": "https://github.com/myetherwallet/myetherwallet#readme",
    "npm_package_dependencies_moment": "2.29.3",
    "npm_package_dependencies__ethereumjs_tx": "3.5.1",
    "NVM_CD_FLAGS": "",
    "npm_config_globalignorefile": "/root/.nvm/versions/node/v12.2.0/etc/npmignore",
    "npm_package_resolutions_glob_parent": "5.1.2",
    "npm_package_devDependencies__vue_cli_plugin_unit_jest": "4.5.15",
    "npm_package_dependencies__shapeshiftoss_hdwallet_keepkey_webusb": "1.21.1",
    "npm_package_dependencies__sentry_tracing": "6.19.7",
    "SHELL": "/bin/bash",
    "TERM": "xterm-256color",
    "npm_config_shell": "/bin/bash",
    "npm_config_maxsockets": "50",
    "npm_config_init_author_url": "",
    "npm_package_devDependencies_vue_template_compiler": "2.6.14",
    "npm_package_dependencies_vue_apollo": "3.1.0",
    "npm_package_scripts_lint_md": "remark . -o",
    "CHAIN_SPEC_PATH": "https://scan.5dax.com/5dax.json",
    "BLOCK_TRANSFORMER": "clique",
    "HISTSIZE": "1000",
    "npm_config_shrinkwrap": "true",
    "npm_config_parseable": "",
    "npm_config_metrics_registry": "https://registry.npmjs.org/",
    "npm_package_resolutions_node_fetch": "2.6.7",
    "SSH_CLIENT": "120.72.83.181 38640 22",
    "npm_config_timing": "",
    "npm_config_init_license": "ISC",
    "npm_package_dependencies_protobufjs": "6.11.2",
    "npm_package_scripts_lint": "npm run lint:code && npm run lint:md",
    "npm_config_if_present": "",
    "npm_package_devDependencies_babel_core": "7.0.0-bridge.0",
    "npm_package_dependencies_crypto": "1.0.1",
    "npm_package_dependencies_apollo_cache_inmemory": "1.6.6",
    "TERM_PROGRAM_VERSION": "1.66.2",
    "npm_package_scripts_dev": "npm run update && npm run juststart",
    "npm_config_sign_git_tag": "",
    "npm_config_init_author_email": "",
    "npm_config_cache_max": "Infinity",
    "npm_package_resolutions_diff": "3.5.0",
    "npm_package_devDependencies_sass_loader": "10.1.1",
    "npm_package_devDependencies__ethersproject_providers": "5.6.4",
    "npm_package_dependencies__lokalise_node_api": "7.2.0",
    "npm_config_preid": "",
    "npm_config_long": "",
    "npm_config_local_address": "",
    "npm_config_git_tag_version": "true",
    "npm_config_cert": "",
    "npm_package_resolutions_y18n": "5.0.5",
    "LOGO": "/images/5dax_logo.svg",
    "npm_config_registry": "https://registry.npmjs.org/",
    "npm_config_noproxy": "",
    "npm_config_fetch_retries": "2",
    "npm_package_devDependencies_multicoin_address_validator": "git+https://github.com/JchainWallet/multicoin-address-validator.git",
    "npm_package_devDependencies__vue_eslint_config_prettier": "6.0.0",
    "npm_package_dependencies__ethereumjs_common": "2.6.4",
    "npm_package_scripts_update_mainlists": "node fetchLists/fetchMainLists.js",
    "npm_package_repository_url": "git+https://github.com/myetherwallet/myetherwallet.git",
    "npm_package_devDependencies_vue_i18n": "8.27.0",
    "npm_package_devDependencies_stylelint_config_standard": "25.0.0",
    "npm_package_dependencies_lottie_web": "5.9.2",
    "npm_package_dependencies_highcharts_vue": "1.4.0",
    "npm_package_scripts_apollo_aave": "apollo service:download -c=apolloAave.config.js src/dapps/aave-dapp/apollo/schemas/api.json && apollo client:codegen -c=apolloAave.config.js src/dapps/aave-dapp/apollo/global/globalTypes.json --target=json",
    "npm_package_scripts_apollo_schema": "apollo service:download src/apollo/schemas/api.json",
    "LOGO_HEADER": "/images/5dax_logo.svg",
    "LC_ALL": "en_US.UTF-8",
    "npm_config_versions": "",
    "npm_config_message": "%s",
    "npm_config_key": "",
    "npm_package_readmeFilename": "README.md",
    "npm_package_dependencies__sentry_browser": "6.19.7",
    "npm_package_dependencies__myetherwallet_eth2_keystore": "0.2.3",
    "DISABLE_EXCHANGE_RATES": "true",
    "npm_package_devDependencies_webpack": "4.44.2",
    "npm_package_devDependencies_print_js": "1.6.0",
    "npm_package_devDependencies_bip39": "3.0.4",
    "npm_package_dependencies_graphql_tag": "2.12.6",
    "npm_package_description": "Client side ethereum wallet",
    "NVM_DIR": "/root/.nvm",
    "USER": "root",
    "npm_package_license": "MIT",
    "npm_package_dependencies_apollo_link_http": "1.5.17",
    "npm_package_dependencies__aave_protocol_js": "1.0.3",
    "npm_package_scripts_build_offline": "WEBPACK_INTEGRITY=false npm run build:hash",
    "LS_COLORS": "rs=0:di=38;5;27:ln=38;5;51:mh=44;38;5;15:pi=40;38;5;11:so=38;5;13:do=38;5;5:bd=48;5;232;38;5;11:cd=48;5;232;38;5;3:or=48;5;232;38;5;9:mi=05;48;5;232;38;5;15:su=48;5;196;38;5;15:sg=48;5;11;38;5;16:ca=48;5;196;38;5;226:tw=48;5;10;38;5;16:ow=48;5;10;38;5;21:st=48;5;21;38;5;15:ex=38;5;34:*.tar=38;5;9:*.tgz=38;5;9:*.arc=38;5;9:*.arj=38;5;9:*.taz=38;5;9:*.lha=38;5;9:*.lz4=38;5;9:*.lzh=38;5;9:*.lzma=38;5;9:*.tlz=38;5;9:*.txz=38;5;9:*.tzo=38;5;9:*.t7z=38;5;9:*.zip=38;5;9:*.z=38;5;9:*.Z=38;5;9:*.dz=38;5;9:*.gz=38;5;9:*.lrz=38;5;9:*.lz=38;5;9:*.lzo=38;5;9:*.xz=38;5;9:*.bz2=38;5;9:*.bz=38;5;9:*.tbz=38;5;9:*.tbz2=38;5;9:*.tz=38;5;9:*.deb=38;5;9:*.rpm=38;5;9:*.jar=38;5;9:*.war=38;5;9:*.ear=38;5;9:*.sar=38;5;9:*.rar=38;5;9:*.alz=38;5;9:*.ace=38;5;9:*.zoo=38;5;9:*.cpio=38;5;9:*.7z=38;5;9:*.rz=38;5;9:*.cab=38;5;9:*.jpg=38;5;13:*.jpeg=38;5;13:*.gif=38;5;13:*.bmp=38;5;13:*.pbm=38;5;13:*.pgm=38;5;13:*.ppm=38;5;13:*.tga=38;5;13:*.xbm=38;5;13:*.xpm=38;5;13:*.tif=38;5;13:*.tiff=38;5;13:*.png=38;5;13:*.svg=38;5;13:*.svgz=38;5;13:*.mng=38;5;13:*.pcx=38;5;13:*.mov=38;5;13:*.mpg=38;5;13:*.mpeg=38;5;13:*.m2v=38;5;13:*.mkv=38;5;13:*.webm=38;5;13:*.ogm=38;5;13:*.mp4=38;5;13:*.m4v=38;5;13:*.mp4v=38;5;13:*.vob=38;5;13:*.qt=38;5;13:*.nuv=38;5;13:*.wmv=38;5;13:*.asf=38;5;13:*.rm=38;5;13:*.rmvb=38;5;13:*.flc=38;5;13:*.avi=38;5;13:*.fli=38;5;13:*.flv=38;5;13:*.gl=38;5;13:*.dl=38;5;13:*.xcf=38;5;13:*.xwd=38;5;13:*.yuv=38;5;13:*.cgm=38;5;13:*.emf=38;5;13:*.axv=38;5;13:*.anx=38;5;13:*.ogv=38;5;13:*.ogx=38;5;13:*.aac=38;5;45:*.au=38;5;45:*.flac=38;5;45:*.mid=38;5;45:*.midi=38;5;45:*.mka=38;5;45:*.mp3=38;5;45:*.mpc=38;5;45:*.ogg=38;5;45:*.ra=38;5;45:*.wav=38;5;45:*.axa=38;5;45:*.oga=38;5;45:*.spx=38;5;45:*.xspf=38;5;45:",
    "npm_config_globalconfig": "/root/.nvm/versions/node/v12.2.0/etc/npmrc",
    "npm_package_dependencies_apollo_link_rest": "0.9.0-rc.1",
    "npm_config_prefer_online": "",
    "npm_config_logs_max": "10",
    "npm_config_always_auth": "",
    "npm_package_resolutions_axios": "0.26.1",
    "npm_package_devDependencies_uglify_es": "3.3.9",
    "npm_package_devDependencies_postcss_url": "8.0.0",
    "npm_package_devDependencies_codecov": "3.8.3",
    "npm_package_devDependencies_bignumber_js": "9.0.2",
    "npm_package_devDependencies_babel_jest": "27.5.1",
    "npm_package_devDependencies_ethereumjs_wallet": "1.0.2",
    "npm_package_devDependencies_eth_ens_namehash": "2.0.8",
    "npm_package_devDependencies__vue_cli_service": "4.5.15",
    "npm_package_dependencies_walletlink": "2.5.0",
    "npm_package_dependencies_lodash": "4.17.21",
    "npm_package_devDependencies_web3_core_method": "1.5.0",
    "npm_package_devDependencies_eslint": "7.32.0",
    "npm_execpath": "/root/.nvm/versions/node/v12.2.0/lib/node_modules/npm/bin/npm-cli.js",
    "npm_config_global_style": "",
    "npm_config_cache_lock_retries": "10",
    "npm_package_resolutions_shelljs": "0.8.5",
    "npm_package_dependencies_package_json": "7.0.0",
    "npm_package_dependencies_graphql": "16.4.0",
    "npm_package_dependencies_apollo_link_ws": "1.0.20",
    "npm_package_dependencies__myetherwallet_mewconnect_web_client": "2.2.0-beta.16",
    "npm_config_update_notifier": "true",
    "npm_config_cafile": "",
    "npm_package_resolutions_dns_packet": "5.2.2",
    "npm_package_dependencies__coolwallets_wallet": "0.2.0-beta.1",
    "npm_package_scripts_apollo_codegen": "npm run apollo:schema && apollo client:codegen src/apollo/global/globalTypes.json --target=json",
    "npm_config_heading": "npm",
    "npm_config_audit_level": "low",
    "npm_package_resolutions_elliptic": "6.5.4",
    "npm_package_devDependencies_eslint_plugin_prettier": "4.0.0",
    "npm_package_devDependencies_copy_webpack_plugin": "6.3.2",
    "npm_package_dependencies__ensdomains_ensjs": "2.1.0",
    "npm_config_searchlimit": "20",
    "npm_config_read_only": "",
    "npm_config_offline": "",
    "npm_config_fetch_retry_mintimeout": "10000",
    "npm_config_json": "",
    "npm_config_access": "",
    "npm_config_argv": "{\"remain\":[],\"cooked\":[\"run\",\"build\"],\"original\":[\"run\",\"build\"]}",
    "npm_package_devDependencies_uuid": "8.3.2",
    "npm_package_devDependencies_hdkey": "2.0.1",
    "npm_package_devDependencies__vue_cli_plugin_pwa": "4.5.15",
    "MAIL": "/var/spool/mail/root",
    "PATH": "/root/.nvm/versions/node/v12.2.0/lib/node_modules/npm/node_modules/npm-lifecycle/node-gyp-bin:/root/MEW/SardisChain/JchainWallet/node_modules/.bin:/root/.vscode-server/bin/dfd34e8260c270da74b5c2d86d61aee4b6d56977/bin/remote-cli:/root/.cargo/bin:/root/.nvm/versions/node/v12.2.0/bin:/opt/elixir/bin:/usr/local/bin:/usr/bin:/bin:/usr/local/sbin:/usr/sbin:/sbin:$PATH:/var/lib/snapd/snap/bin:/root/bin",
    "npm_config_allow_same_version": "",
    "npm_package_resolutions_scrypt_js": "0.3.0",
    "npm_package_devDependencies_minizlib": "2.1.2",
    "npm_package_devDependencies_bc_vault_js": "2.1.1",
    "npm_package_dependencies_bitbox02_api": "0.14.0",
    "LINK_TO_OTHER_EXPLORERS": "false",
    "npm_config_https_proxy": "",
    "npm_config_engine_strict": "",
    "npm_config_description": "true",
    "npm_package_devDependencies_html2canvas": "1.4.1",
    "npm_package_dependencies_vue": "2.6.14",
    "COIN": "5T",
    "npm_config_userconfig": "/root/.npmrc",
    "npm_config_init_module": "/root/.npm-init.js",
    "npm_package_resolutions_xmlhttprequest_ssl": "1.6.2",
    "npm_package_devDependencies_commitlint": "16.2.4",
    "npm_package_dependencies_platform": "1.3.6",
    "SECRET_KEY_BASE": "HWEcCg9Z0KLPD9ty9fyOBCrJgpBhyUa19hCSJTwLdiS0MW4zzsdN/vgSrLnRosyJ",
    "ETHEREUM_JSONRPC_WS_URL": "ws://localhost:1546",
    "npm_config_cidr": "",
    "npm_package_devDependencies_node_fetch": "2.6.7",
    "npm_package_dependencies__actions_github": "5.0.1",
    "PWD": "/root/MEW/SardisChain/JchainWallet",
    "npm_config_user": "",
    "npm_config_node_version": "12.2.0",
    "npm_package_bugs_url": "https://github.com/myetherwallet/myetherwallet/issues",
    "npm_package_devDependencies_remark_preset_lint_recommended": "6.1.2",
    "npm_package_dependencies_keccak256": "1.0.6",
    "npm_package_dependencies__ensdomains_ens_contracts": "0.0.11",
    "npm_lifecycle_event": "build",
    "npm_package_devDependencies_trezor_connect": "8.2.8",
    "npm_package_devDependencies_remark_cli": "10.0.0",
    "npm_package_scripts_apollo": "apollo",
    "npm_config_save": "true",
    "npm_config_ignore_prepublish": "",
    "npm_config_editor": "vi",
    "npm_config_auth_type": "legacy",
    "npm_package_repository_type": "git",
    "npm_package_resolutions_cryptiles": "4.1.2",
    "npm_package_devDependencies_eslint_plugin_security": "1.5.0",
    "npm_package_name": "myetherwallet",
    "LANG": "en_US.UTF-8",
    "npm_config_tag": "latest",
    "npm_config_script_shell": "",
    "npm_package_devDependencies_stylelint_config_prettier": "9.0.3",
    "npm_config_progress": "true",
    "npm_config_global": "",
    "npm_config_before": "",
    "npm_package_devDependencies_sass": "1.34.1",
    "npm_package_devDependencies__vue_test_utils": "1.3.0",
    "npm_package_scripts_start": "npm run update:mainlists && npm run dev",
    "npm_package_scripts_preinstall": "find node_modules -name \".git\" -exec rm -rf {} \\; || true && bash ./scripts/checklockconflicts.sh && npx npm-force-resolutions",
    "npm_package_scripts_build": "npm run update && vue-cli-service build",
    "npm_config_searchstaleness": "900",
    "npm_config_optional": "true",
    "npm_config_ham_it_up": "",
    "npm_package_devDependencies_web3_core_helpers": "1.5.0",
    "npm_package_dependencies_qr_code_styling": "1.6.0-rc.1",
    "npm_package_dependencies_clipboard_copy": "4.0.1",
    "VSCODE_GIT_ASKPASS_EXTRA_ARGS": "",
    "npm_config_save_prod": "",
    "npm_config_force": "",
    "npm_config_bin_links": "true",
    "npm_package_resolutions_normalize_url": "6.0.1",
    "npm_package_devDependencies_stylelint": "14.7.1",
    "npm_package_dependencies__coolwallets_transport_web_ble": "0.1.0",
    "npm_config_searchopts": "",
    "npm_package_resolutions_socket_io_parser": "3.4.1",
    "npm_package_engines_node": ">= 10.0.0 < 12.3.0",
    "npm_package_devDependencies_is_ipfs": "6.0.2",
    "LOGO_FOOTER": "/images/5dax_logo.svg",
    "CURRENCY": "5T",
    "npm_config_node_gyp": "/root/.nvm/versions/node/v12.2.0/lib/node_modules/npm/node_modules/node-gyp/bin/node-gyp.js",
    "npm_config_depth": "Infinity",
    "MIX_ENV": "prod",
    "npm_config_sso_poll_frequency": "500",
    "npm_config_rebuild_bundle": "true",
    "npm_package_resolutions_keccak": "3.0.1",
    "npm_package_dependencies__walletconnect_client": "1.7.8",
    "npm_package_dependencies__coolwallets_eth": "0.2.0-beta.1",
    "npm_package_scripts_lint_tests": "eslint --fix tests/",
    "npm_package_version": "6.5.1",
    "HISTCONTROL": "ignoredups",
    "npm_config_unicode": "true",
    "npm_package_devDependencies_vue_cli_plugin_vuetify": "2.4.8",
    "npm_package_scripts_build_history_sourcemaps": "ROUTER_MODE=history FULL_SOURCEMAPS=true npm run build",
    "npm_package_resolutions_node_forge": "1.3.0",
    "npm_package_devDependencies__vue_cli_plugin_babel": "4.5.15",
    "SHLVL": "6",
    "HOME": "/root",
    "npm_config_fetch_retry_maxtimeout": "60000",
    "npm_package_resolutions_simple_get": "4.0.1",
    "npm_package_devDependencies_xss": "1.0.11",
    "npm_package_devDependencies_eslint_plugin_vue": "8.7.1",
    "npm_package_devDependencies__vue_babel_preset_app": "4.5.15",
    "npm_package_dependencies_highcharts": "10.0.0",
    "npm_package_dependencies_apollo_client": "2.6.10",
    "npm_package_scripts_test": "npm run update:lists && jest --clearCache && npm run test:unit",
    "BLOCKSCOUT_PROTOCOL": "http",
    "LANGUAGE": "en_US",
    "VSCODE_GIT_ASKPASS_MAIN": "/root/.vscode-server/bin/dfd34e8260c270da74b5c2d86d61aee4b6d56977/extensions/git/dist/askpass-main.js",
    "npm_config_tag_version_prefix": "v",
    "npm_config_strict_ssl": "true",
    "npm_config_sso_type": "oauth",
    "npm_config_scripts_prepend_node_path": "warn-only",
    "npm_config_save_prefix": "^",
    "npm_config_loglevel": "notice",
    "npm_config_ca": "",
    "npm_package_resolutions_css_what": "5.0.1",
    "npm_package_resolutions_trim_newlines": "3.0.1",
    "npm_package_devDependencies_store": "2.0.12",
    "npm_package_devDependencies_simple_get": "4.0.1",
    "npm_package_dependencies_register_service_worker": "1.7.2",
    "npm_package_scripts_update_lists": "node fetchLists/index.js",
    "npm_package_scripts_codecov": "npm run test && codecov",
    "npm_config_save_exact": "",
    "npm_config_group": "",
    "npm_config_fetch_retry_factor": "10",
    "npm_config_dev": "",
    "npm_package_devDependencies_imagemin_mozjpeg": "9.0.0",
    "npm_package_devDependencies_husky": "5.0.9",
    "npm_package_devDependencies_babel_eslint": "10.1.0",
    "npm_config_version": "",
    "npm_config_prefer_offline": "",
    "npm_config_cache_lock_stale": "60000",
    "npm_package_scripts_update": "npm run update:packages && npm run update:lists",
    "npm_config_otp": "",
    "npm_config_cache_min": "10",
    "npm_package_resolutions_tar": "4.4.18",
    "npm_package_devDependencies_vue_matomo": "4.1.0",
    "ETHEREUM_JSONRPC_HTTP_URL": "http://localhost:1545",
    "npm_config_searchexclude": "",
    "npm_config_cache": "/root/.npm",
    "npm_package_devDependencies__ledgerhq_hw_app_eth": "6.26.1",
    "npm_package_dependencies__ensdomains_address_encoder": "0.2.17",
    "npm_package_scripts_start_history": "npm run update:mainlists && ROUTER_MODE=history npm run dev",
    "npm_package_scripts_build_history": "ROUTER_MODE=history npm run build",
    "LOGNAME": "root",
    "npm_lifecycle_script": "npm run update && vue-cli-service build",
    "npm_config_color": "true",
    "npm_package_resolutions_url_parse": "1.5.10",
    "npm_package_devDependencies__vue_cli_plugin_eslint": "4.5.15",
    "npm_package_devDependencies__ledgerhq_hw_transport_webusb": "6.27.1",
    "npm_package_scripts_juststart": "vue-cli-service serve --watch",
    "ECTO_USE_SSL": "false",
    "npm_config_proxy": "",
    "npm_config_package_lock": "true",
    "npm_package_devDependencies_imagemin_webpack_plugin": "2.4.2",
    "npm_package_dependencies_vuex": "3.6.2",
    "XDG_DATA_DIRS": "/usr/local/share:/usr/share:/var/lib/snapd/desktop",
    "LC_CTYPE": "en_US.UTF-8",
    "SSH_CONNECTION": "120.72.83.181 38640 202.143.111.98 22",
    "VSCODE_GIT_IPC_HANDLE": "/run/user/0/vscode-git-b0c985fefa.sock",
    "npm_config_package_lock_only": "",
    "npm_package_resolutions_engine_io": "4.1.2",
    "npm_package_devDependencies_vuetify": "2.5.9",
    "npm_package_dependencies_ethers": "5.6.4",
    "VSCODE_IPC_HOOK_CLI": "/run/user/0/vscode-ipc-48654aba-771b-4398-a024-9ba4d32ece4b.sock",
    "npm_config_save_optional": "",
    "npm_package_devDependencies__ethersproject_units": "5.6.0",
    "npm_package_dependencies_apollo_link": "1.2.14",
    "NVM_BIN": "/root/.nvm/versions/node/v12.2.0/bin",
    "LESSOPEN": "||/usr/bin/lesspipe.sh %s",
    "npm_config_ignore_scripts": "",
    "npm_config_user_agent": "npm/6.9.0 node/v12.2.0 linux x64",
    "npm_package_devDependencies_u2f_api": "1.2.1",
    "npm_package_dependencies_apollo_link_error": "1.1.13",
    "npm_package_dependencies__sentry_vue": "6.19.7",
    "BROWSER": "/root/.vscode-server/bin/dfd34e8260c270da74b5c2d86d61aee4b6d56977/bin/helpers/browser.sh",
    "npm_config_cache_lock_wait": "10000",
    "npm_package_devDependencies_web3": "1.5.0",
    "npm_package_devDependencies_jest_skipped_reporter": "0.0.5",
    "PORT": "4000",
    "VSCODE_GIT_ASKPASS_NODE": "/root/.vscode-server/bin/dfd34e8260c270da74b5c2d86d61aee4b6d56977/node",
    "GIT_ASKPASS": "/root/.vscode-server/bin/dfd34e8260c270da74b5c2d86d61aee4b6d56977/extensions/git/dist/askpass.sh",
    "npm_config_production": "",
    "npm_package_devDependencies_ethereumjs_common": "1.5.2",
    "npm_package_devDependencies_axios": "0.27.2",
    "npm_package_dependencies_animejs": "3.2.1",
    "npm_package_dependencies__walletconnect_qrcode_modal": "1.7.8",
    "XDG_RUNTIME_DIR": "/run/user/0",
    "npm_config_send_metrics": "",
    "npm_config_save_bundle": "",
    "npm_package_resolutions_bl": "4.0.3",
    "npm_package_devDependencies__mdi_font": "6.6.96",
    "npm_package_scripts_prepare": "husky install",
    "ETHEREUM_JSONRPC_VARIANT": "geth",
    "npm_config_umask": "0022",
    "npm_config_node_options": "",
    "npm_config_init_version": "1.0.0",
    "npm_package_devDependencies_raw_loader": "4.0.2",
    "npm_package_dependencies__myetherwallet_mew_components": "1.0.0",
    "npm_config_init_author_name": "",
    "npm_config_git": "git",
    "npm_config_scope": "",
    "npm_package_resolutions_handlebars": "4.7.7",
    "npm_package_devDependencies_node_sass": "7.0.1",
    "npm_package_devDependencies__commitlint_config_conventional": "16.2.4",
    "npm_package_dependencies_vue_router": "3.5.3",
    "npm_package_scripts_build_hash": "ROUTER_MODE=hash npm run build",
    "DATABASE_URL": "postgresql://nexdax:nexdax123!@localhost:5432/nexdax_explorer",
    "npm_config_unsafe_perm": "",
    "npm_config_tmp": "/tmp",
    "npm_config_onload_script": "",
    "npm_node_execpath": "/root/.nvm/versions/node/v12.2.0/bin/node",
    "npm_config_prefix": "/root/.nvm/versions/node/v12.2.0",
    "npm_config_link": "",
    "npm_package_dependencies__unstoppabledomains_resolution": "7.1.4",
    "npm_package_scripts_update_packages": "node package-test.js",
    "npm_package_scripts_test_unit": "vue-cli-service test:unit --logHeapUsage",
    "COLORTERM": "truecolor",
    "_": "/root/MEW/SardisChain/JchainWallet/node_modules/.bin/vue-cli-service",
    "NODE_ENV": "production",
    "INLINE_RUNTIME_CHUNK": "false",
    "FULL_SOURCEMAPS": "false",
    "BABEL_ENV": "production",
    "VUE_CLI_TRANSPILE_BABEL_RUNTIME": "true",
    "VUE_CLI_BUILD_TARGET": "app",
    "VUE_CLI_ENTRY_FILES": "[\"/root/MEW/SardisChain/JchainWallet/src/main.js\"]"
  },
  "userLimits": {
    "core_file_size_blocks": {
      "soft": 0,
      "hard": "unlimited"
    },
    "data_seg_size_kbytes": {
      "soft": "unlimited",
      "hard": "unlimited"
    },
    "file_size_blocks": {
      "soft": "unlimited",
      "hard": "unlimited"
    },
    "max_locked_memory_bytes": {
      "soft": 65536,
      "hard": 65536
    },
    "max_memory_size_kbytes": {
      "soft": "unlimited",
      "hard": "unlimited"
    },
    "open_files": {
      "soft": 4096,
      "hard": 4096
    },
    "stack_size_bytes": {
      "soft": 8388608,
      "hard": "unlimited"
    },
    "cpu_time_seconds": {
      "soft": "unlimited",
      "hard": "unlimited"
    },
    "max_user_processes": {
      "soft": 63383,
      "hard": 63383
    },
    "virtual_memory_kbytes": {
      "soft": "unlimited",
      "hard": "unlimited"
    }
  },
  "sharedObjects": [
    "/lib64/libdl.so.2",
    "/lib64/librt.so.1",
    "/lib64/libstdc++.so.6",
    "/lib64/libm.so.6",
    "/lib64/libgcc_s.so.1",
    "/lib64/libpthread.so.0",
    "/lib64/libc.so.6",
    "/lib64/ld-linux-x86-64.so.2",
    "/root/MEW/SardisChain/JchainWallet/node_modules/fibers/bin/linux-x64-72-glibc/fibers.node"
  ]
}